wattpad_scraper/__init__.py
wattpad_scraper/cli.py
wattpad_scraper/main.py
wattpad_scraper/print_utils.py
wattpad_scraper/core/__init__.py
wattpad_scraper/core/epub_exporter.py
wattpad_scraper/core/extractor.py
wattpad_scraper-1.0.0.dist-info/METADATA
wattpad_scraper-1.0.0.dist-info/WHEEL
wattpad_scraper-1.0.0.dist-info/entry_points.txt
wattpad_scraper-1.0.0.dist-info/top_level.txt
wattpad_scraper-1.0.0.dist-info/RECORD
