Metadata-Version: 2.4
Name: wattpad-scraper
Version: 1.0.0
Summary: Automagically download any Wattpad book as an EPUB file. (new Wattpad update supported)
Author-email: fen <notfenixi0@proton.me>
Requires-Python: >=3.12
Requires-Dist: beautifulsoup4>=4.13.4
Requires-Dist: colorama>=0.4.6
Requires-Dist: ebooklib>=0.19
Requires-Dist: pygments>=2.19.2
Requires-Dist: pytest>=8.4.1
Requires-Dist: requests>=2.32.3
